fpl_exporter/__init__.py
fpl_exporter/api.py
fpl_exporter/cli.py
fpl_exporter/exceptions.py
fpl_exporter/fpl_exporter.py
fpl_exporter/metrics.py
fpl_exporter-0.1.5.dist-info/AUTHORS.rst
fpl_exporter-0.1.5.dist-info/LICENSE
fpl_exporter-0.1.5.dist-info/METADATA
fpl_exporter-0.1.5.dist-info/WHEEL
fpl_exporter-0.1.5.dist-info/entry_points.txt
fpl_exporter-0.1.5.dist-info/top_level.txt
fpl_exporter-0.1.5.dist-info/RECORD
