Metadata-Version: 2.1
Name: fpl-exporter
Version: 0.1.5
Summary: Prometheus Exporter for Fantasy Premier League.
Home-page: https://github.com/P6rguvyrst/FPLExporter
Author: Toomas Ormisson
Author-email: contact@verypythonproblems.com
License: Apache Software License 2.0
Keywords: fpl_exporter fpl premierleague fantasypremierleague prometheus exporter
Platform: UNKNOWN
Classifier: Development Status :: 2 - Pre-Alpha
Classifier: Intended Audience :: Developers
Classifier: License :: OSI Approved :: Apache Software License
Classifier: Natural Language :: English
Classifier: Programming Language :: Python :: 3
Classifier: Programming Language :: Python :: 3.6
Classifier: Programming Language :: Python :: 3.7
Requires-Dist: Click (>=6.0)
Requires-Dist: requests
Requires-Dist: prometheus-client
Requires-Dist: responses
